openaiapi/__init__.py
openaiapi/py.typed
openaiapi-0.0.2.dist-info/LICENSE
openaiapi-0.0.2.dist-info/METADATA
openaiapi-0.0.2.dist-info/WHEEL
openaiapi-0.0.2.dist-info/top_level.txt
openaiapi-0.0.2.dist-info/RECORD
