Metadata-Version: 2.1
Name: openaiapi
Version: 0.0.2
Summary: A light wrapper around the OpenAI API using apiron
Home-page: https://github.com/daneah/openaiapi
Author: Dane Hillard
Author-email: "Dane Hillard" <github@danehillard.com>
License: MIT License
Classifier: License :: OSI Approved :: MIT License
Requires-Python: >=3.9
License-File: LICENSE
Requires-Dist: apiron (>=7.0.0)
Requires-Dist: urllib3 (<2,>=1.26.13)
